{"requestDetails":{"dateOfRequest":"09-06-2022","reportId":"CCR220609CR718436762","batchId":"1499368349220609"},"personalInformation":{"nameVariations":[{"value":"AISHWARY MISALE","reportedDate":"31-03-2022"},{"value":"B'AISHWARY' B'MISALE'","reportedDate":"30-04-2022"},{"value":"AISHWARY VINODRAO MISALE","reportedDate":"31-12-2021"}],"addressVariations":[{"value":"NEAR POST OFFICE WARD NO 4 WARUD 442302 MH","reportedDate":"04-05-2021"},{"value":"S O VINODRAO MISALE NEAR POST OFFICE WARD NO 4 WARUD AMRAVATI MAHARASHTRA 444906 444906 MH","reportedDate":"31-03-2022"},{"value":"NEAR POST OFFICE WARD NO 4 B'WARUD' AMRA VATI AMRAVATI MH 444906 444906 MH","reportedDate":"30-04-2022"},{"value":"NEAR POST OFFICE PANDHURANG KRUPA POLICE STATION ROAD WARUD  MAHARASHTRA 444906 444906 MH","reportedDate":"31-12-2021"}],"panVariations":[{"value":"GHXPM2781Q","reportedDate":"30-04-2022"}],"uidVariations":[{"value":"XXXXXXXX7816","reportedDate":"04-05-2021"}],"otherIdVariations":[],"drivingLicenseVariations":[{"value":"MH2720190010733","reportedDate":"31-12-2021"}],"dateOfBirthVariations":[{"value":"03-09-2000","reportedDate":"31-03-2021"},{"value":"19-09-2000","reportedDate":"31-12-2021"}],"voterIdVariations":[],"passportVariations":[],"phoneNumberVariations":[{"value":"9421635218","reportedDate":"31-12-2021"},{"value":"7769944733","reportedDate":"30-04-2022"}],"rationCardVariations":[],"emailVariations":[{"value":"aishwarymisale@gmail.com","reportedDate":"30-04-2022"},{"value":"aishwarymisale1909@gmail.com","reportedDate":"30-04-2022"}]},"tradesSummary":[{"accountNumber":"MK794A617BID25241186","accountType":"Personal Loan","dateReported":"31-12-2021","accountStatus":"Closed","disbursedAmount":"500","disbursedDate":"10-11-2021","lastPaymentDate":"11-12-2021","closeDate":null,"installmentAmount":null,"interestRate":null,"overdueAmount":"0","writeoffAmount":"0","currentBalance":"0","creditLimit":null,"accountRemarks":null,"frequency":null,"combinedPaymentHistory":"Dec:2021,000/XXX|Nov:2021,XXX/STD|","cashLimit":null,"actualPayment":null,"repaymentTenure":null,"disbursedAmountInt":500,"currentBalanceInt":0,"overdueAmtInt":0,"writeoffAmountInt":0,"creditLimitInt":0,"latestMonthPayment":{"month":"Dec","year":"2021","dpd":0,"assetClassificationCode":"XXX","distanceFromReportDate":6},"totalPayments":2,"installmentAmountInt":17,"isActive":false,"isWrittenOff":false,"isClosed":true,"internalAccountType":"personal","isWrittenOffBasedOnLatestPayment":false,"isDelinquent":false,"isClosedAndNotWrittenOff":true,"noOfMonthsBtwReportDateAndDisbursalDate":6,"maxDpdInLast1Month":0,"maxDpdInLast3Months":0,"maxDpdInLast6Months":0,"maxDpdInLast9Months":0,"maxDpdInLast12Months":0,"noOfTimesDefaulted":0,"isDpdAtLeastOnce":false,"isDpdThirtyAtLeastOnce":false,"isDpdSixtyAtLeastOnce":false,"isDpdNinetyAtLeastOnce":false,"noOfDpdThirtyInLast3Months":0,"noOfDpdThirtyInLast6Months":0,"noOfDpdThirtyInLast9Months":0,"noOfDpdThirtyInLast12Months":0,"noOfDpdThirtyInLast24Months":0,"noOfDpdSixtyInLast3Months":0,"noOfDpdSixtyInLast6Months":0,"noOfDpdSixtyInLast9Months":0,"noOfDpdSixtyInLast12Months":0,"noOfDpdSixtyInLast24Months":0,"noOfDpdOneInLast3Months":0},{"accountNumber":"MKB87C615DID21406231","accountType":"Personal Loan","dateReported":"31-08-2021","accountStatus":"Active","disbursedAmount":"500","disbursedDate":"10-08-2021","lastPaymentDate":null,"closeDate":null,"installmentAmount":null,"interestRate":null,"overdueAmount":null,"writeoffAmount":"0","currentBalance":"525","creditLimit":null,"accountRemarks":null,"frequency":null,"combinedPaymentHistory":"Aug:2021,XXX/STD|","cashLimit":null,"actualPayment":null,"repaymentTenure":null,"disbursedAmountInt":500,"currentBalanceInt":525,"overdueAmtInt":0,"writeoffAmountInt":0,"creditLimitInt":0,"latestMonthPayment":{"month":"Aug","year":"2021","dpd":0,"assetClassificationCode":"STD","distanceFromReportDate":10},"totalPayments":1,"installmentAmountInt":17,"isActive":false,"isWrittenOff":false,"isClosed":true,"internalAccountType":"personal","isWrittenOffBasedOnLatestPayment":false,"isDelinquent":false,"isClosedAndNotWrittenOff":true,"noOfMonthsBtwReportDateAndDisbursalDate":9,"maxDpdInLast1Month":0,"maxDpdInLast3Months":0,"maxDpdInLast6Months":0,"maxDpdInLast9Months":0,"maxDpdInLast12Months":0,"noOfTimesDefaulted":0,"isDpdAtLeastOnce":false,"isDpdThirtyAtLeastOnce":false,"isDpdSixtyAtLeastOnce":false,"isDpdNinetyAtLeastOnce":false,"noOfDpdThirtyInLast3Months":0,"noOfDpdThirtyInLast6Months":0,"noOfDpdThirtyInLast9Months":0,"noOfDpdThirtyInLast12Months":0,"noOfDpdThirtyInLast24Months":0,"noOfDpdSixtyInLast3Months":0,"noOfDpdSixtyInLast6Months":0,"noOfDpdSixtyInLast9Months":0,"noOfDpdSixtyInLast12Months":0,"noOfDpdSixtyInLast24Months":0,"noOfDpdOneInLast3Months":0},{"accountNumber":"MKDB99618CID25241288","accountType":"Personal Loan","dateReported":"31-12-2021","accountStatus":"Closed","disbursedAmount":"500","disbursedDate":"10-11-2021","lastPaymentDate":"11-12-2021","closeDate":null,"installmentAmount":null,"interestRate":null,"overdueAmount":"0","writeoffAmount":"0","currentBalance":"0","creditLimit":null,"accountRemarks":null,"frequency":null,"combinedPaymentHistory":"Dec:2021,000/XXX|Nov:2021,XXX/STD|","cashLimit":null,"actualPayment":null,"repaymentTenure":null,"disbursedAmountInt":500,"currentBalanceInt":0,"overdueAmtInt":0,"writeoffAmountInt":0,"creditLimitInt":0,"latestMonthPayment":{"month":"Dec","year":"2021","dpd":0,"assetClassificationCode":"XXX","distanceFromReportDate":6},"totalPayments":2,"installmentAmountInt":17,"isActive":false,"isWrittenOff":false,"isClosed":true,"internalAccountType":"personal","isWrittenOffBasedOnLatestPayment":false,"isDelinquent":false,"isClosedAndNotWrittenOff":true,"noOfMonthsBtwReportDateAndDisbursalDate":6,"maxDpdInLast1Month":0,"maxDpdInLast3Months":0,"maxDpdInLast6Months":0,"maxDpdInLast9Months":0,"maxDpdInLast12Months":0,"noOfTimesDefaulted":0,"isDpdAtLeastOnce":false,"isDpdThirtyAtLeastOnce":false,"isDpdSixtyAtLeastOnce":false,"isDpdNinetyAtLeastOnce":false,"noOfDpdThirtyInLast3Months":0,"noOfDpdThirtyInLast6Months":0,"noOfDpdThirtyInLast9Months":0,"noOfDpdThirtyInLast12Months":0,"noOfDpdThirtyInLast24Months":0,"noOfDpdSixtyInLast3Months":0,"noOfDpdSixtyInLast6Months":0,"noOfDpdSixtyInLast9Months":0,"noOfDpdSixtyInLast12Months":0,"noOfDpdSixtyInLast24Months":0,"noOfDpdOneInLast3Months":0},{"accountNumber":"MK2C7A6003ID19883496","accountType":"Personal Loan","dateReported":"31-08-2021","accountStatus":"Active","disbursedAmount":"500","disbursedDate":"02-07-2021","lastPaymentDate":null,"closeDate":null,"installmentAmount":null,"interestRate":null,"overdueAmount":null,"writeoffAmount":"0","currentBalance":"550","creditLimit":null,"accountRemarks":null,"frequency":null,"combinedPaymentHistory":"Aug:2021,XXX/STD|Jul:2021,XXX/STD|","cashLimit":null,"actualPayment":null,"repaymentTenure":null,"disbursedAmountInt":500,"currentBalanceInt":550,"overdueAmtInt":0,"writeoffAmountInt":0,"creditLimitInt":0,"latestMonthPayment":{"month":"Aug","year":"2021","dpd":0,"assetClassificationCode":"STD","distanceFromReportDate":10},"totalPayments":2,"installmentAmountInt":17,"isActive":false,"isWrittenOff":false,"isClosed":true,"internalAccountType":"personal","isWrittenOffBasedOnLatestPayment":false,"isDelinquent":false,"isClosedAndNotWrittenOff":true,"noOfMonthsBtwReportDateAndDisbursalDate":11,"maxDpdInLast1Month":0,"maxDpdInLast3Months":0,"maxDpdInLast6Months":0,"maxDpdInLast9Months":0,"maxDpdInLast12Months":0,"noOfTimesDefaulted":0,"isDpdAtLeastOnce":false,"isDpdThirtyAtLeastOnce":false,"isDpdSixtyAtLeastOnce":false,"isDpdNinetyAtLeastOnce":false,"noOfDpdThirtyInLast3Months":0,"noOfDpdThirtyInLast6Months":0,"noOfDpdThirtyInLast9Months":0,"noOfDpdThirtyInLast12Months":0,"noOfDpdThirtyInLast24Months":0,"noOfDpdSixtyInLast3Months":0,"noOfDpdSixtyInLast6Months":0,"noOfDpdSixtyInLast9Months":0,"noOfDpdSixtyInLast12Months":0,"noOfDpdSixtyInLast24Months":0,"noOfDpdOneInLast3Months":0},{"accountNumber":"SL112155","accountType":"Consumer Loan","dateReported":"31-03-2022","accountStatus":"Active","disbursedAmount":"3,500","disbursedDate":"23-11-2019","lastPaymentDate":"04-04-2021","closeDate":null,"installmentAmount":null,"interestRate":null,"overdueAmount":"0","writeoffAmount":"0","currentBalance":"0","creditLimit":null,"accountRemarks":null,"frequency":null,"combinedPaymentHistory":"Mar:2022,000/STD|Feb:2022,000/STD|Jan:2022,000/STD|Dec:2021,000/STD|Nov:2021,000/STD|Oct:2021,000/STD|Sep:2021,000/STD|Aug:2021,000/STD|Jul:2021,000/STD|Jun:2021,000/STD|May:2021,000/STD|Apr:2021,000/STD|Mar:2021,000/STD|Feb:2021,000/STD|Jan:2021,000/STD|Dec:2020,000/STD|Nov:2020,000/STD|Oct:2020,000/STD|Sep:2020,000/STD|Aug:2020,000/STD|Jul:2020,000/STD|Jun:2020,000/STD|May:2020,000/STD|Apr:2020,000/STD|Mar:2020,DDD/DDD|Feb:2020,000/STD|Jan:2020,000/STD|Dec:2019,000/STD|Nov:2019,000/STD|","cashLimit":null,"actualPayment":null,"repaymentTenure":null,"disbursedAmountInt":3500,"currentBalanceInt":0,"overdueAmtInt":0,"writeoffAmountInt":0,"creditLimitInt":0,"latestMonthPayment":{"month":"Mar","year":"2022","dpd":0,"assetClassificationCode":"STD","distanceFromReportDate":3},"totalPayments":29,"installmentAmountInt":213,"isActive":true,"isWrittenOff":false,"isClosed":false,"internalAccountType":"consumer","isWrittenOffBasedOnLatestPayment":false,"isDelinquent":false,"isClosedAndNotWrittenOff":false,"noOfMonthsBtwReportDateAndDisbursalDate":30,"maxDpdInLast1Month":0,"maxDpdInLast3Months":0,"maxDpdInLast6Months":0,"maxDpdInLast9Months":0,"maxDpdInLast12Months":0,"noOfTimesDefaulted":0,"isDpdAtLeastOnce":false,"isDpdThirtyAtLeastOnce":false,"isDpdSixtyAtLeastOnce":false,"isDpdNinetyAtLeastOnce":false,"noOfDpdThirtyInLast3Months":0,"noOfDpdThirtyInLast6Months":0,"noOfDpdThirtyInLast9Months":0,"noOfDpdThirtyInLast12Months":0,"noOfDpdThirtyInLast24Months":0,"noOfDpdSixtyInLast3Months":0,"noOfDpdSixtyInLast6Months":0,"noOfDpdSixtyInLast9Months":0,"noOfDpdSixtyInLast12Months":0,"noOfDpdSixtyInLast24Months":0,"noOfDpdOneInLast3Months":0},{"accountNumber":"MK1ABC6007ID19793639","accountType":"Personal Loan","dateReported":"31-08-2021","accountStatus":"Closed","disbursedAmount":"1,000","disbursedDate":"01-07-2021","lastPaymentDate":"28-08-2021","closeDate":null,"installmentAmount":null,"interestRate":null,"overdueAmount":"0","writeoffAmount":"0","currentBalance":"0","creditLimit":null,"accountRemarks":null,"frequency":null,"combinedPaymentHistory":"Aug:2021,000/XXX|Jul:2021,XXX/STD|","cashLimit":null,"actualPayment":null,"repaymentTenure":null,"disbursedAmountInt":1000,"currentBalanceInt":0,"overdueAmtInt":0,"writeoffAmountInt":0,"creditLimitInt":0,"latestMonthPayment":{"month":"Aug","year":"2021","dpd":0,"assetClassificationCode":"XXX","distanceFromReportDate":10},"totalPayments":2,"installmentAmountInt":33,"isActive":false,"isWrittenOff":false,"isClosed":true,"internalAccountType":"personal","isWrittenOffBasedOnLatestPayment":false,"isDelinquent":false,"isClosedAndNotWrittenOff":true,"noOfMonthsBtwReportDateAndDisbursalDate":11,"maxDpdInLast1Month":0,"maxDpdInLast3Months":0,"maxDpdInLast6Months":0,"maxDpdInLast9Months":0,"maxDpdInLast12Months":0,"noOfTimesDefaulted":0,"isDpdAtLeastOnce":false,"isDpdThirtyAtLeastOnce":false,"isDpdSixtyAtLeastOnce":false,"isDpdNinetyAtLeastOnce":false,"noOfDpdThirtyInLast3Months":0,"noOfDpdThirtyInLast6Months":0,"noOfDpdThirtyInLast9Months":0,"noOfDpdThirtyInLast12Months":0,"noOfDpdThirtyInLast24Months":0,"noOfDpdSixtyInLast3Months":0,"noOfDpdSixtyInLast6Months":0,"noOfDpdSixtyInLast9Months":0,"noOfDpdSixtyInLast12Months":0,"noOfDpdSixtyInLast24Months":0,"noOfDpdOneInLast3Months":0},{"accountNumber":"MK7A806187ID24438067","accountType":"Personal Loan","dateReported":"30-11-2021","accountStatus":"Closed","disbursedAmount":"1,000","disbursedDate":"23-10-2021","lastPaymentDate":"21-11-2021","closeDate":null,"installmentAmount":null,"interestRate":null,"overdueAmount":"0","writeoffAmount":"0","currentBalance":"0","creditLimit":null,"accountRemarks":null,"frequency":null,"combinedPaymentHistory":"Nov:2021,000/XXX|Oct:2021,XXX/STD|","cashLimit":null,"actualPayment":null,"repaymentTenure":null,"disbursedAmountInt":1000,"currentBalanceInt":0,"overdueAmtInt":0,"writeoffAmountInt":0,"creditLimitInt":0,"latestMonthPayment":{"month":"Nov","year":"2021","dpd":0,"assetClassificationCode":"XXX","distanceFromReportDate":7},"totalPayments":2,"installmentAmountInt":33,"isActive":false,"isWrittenOff":false,"isClosed":true,"internalAccountType":"personal","isWrittenOffBasedOnLatestPayment":false,"isDelinquent":false,"isClosedAndNotWrittenOff":true,"noOfMonthsBtwReportDateAndDisbursalDate":7,"maxDpdInLast1Month":0,"maxDpdInLast3Months":0,"maxDpdInLast6Months":0,"maxDpdInLast9Months":0,"maxDpdInLast12Months":0,"noOfTimesDefaulted":0,"isDpdAtLeastOnce":false,"isDpdThirtyAtLeastOnce":false,"isDpdSixtyAtLeastOnce":false,"isDpdNinetyAtLeastOnce":false,"noOfDpdThirtyInLast3Months":0,"noOfDpdThirtyInLast6Months":0,"noOfDpdThirtyInLast9Months":0,"noOfDpdThirtyInLast12Months":0,"noOfDpdThirtyInLast24Months":0,"noOfDpdSixtyInLast3Months":0,"noOfDpdSixtyInLast6Months":0,"noOfDpdSixtyInLast9Months":0,"noOfDpdSixtyInLast12Months":0,"noOfDpdSixtyInLast24Months":0,"noOfDpdOneInLast3Months":0},{"accountNumber":"MK77F16194ID29111688","accountType":"Personal Loan","dateReported":"31-03-2022","accountStatus":"Closed","disbursedAmount":"2,000","disbursedDate":"25-01-2022","lastPaymentDate":"27-03-2022","closeDate":null,"installmentAmount":null,"interestRate":null,"overdueAmount":"0","writeoffAmount":"0","currentBalance":"0","creditLimit":null,"accountRemarks":null,"frequency":null,"combinedPaymentHistory":"Mar:2022,000/XXX|Feb:2022,XXX/STD|Jan:2022,XXX/STD|","cashLimit":null,"actualPayment":null,"repaymentTenure":null,"disbursedAmountInt":2000,"currentBalanceInt":0,"overdueAmtInt":0,"writeoffAmountInt":0,"creditLimitInt":0,"latestMonthPayment":{"month":"Mar","year":"2022","dpd":0,"assetClassificationCode":"XXX","distanceFromReportDate":3},"totalPayments":3,"installmentAmountInt":66,"isActive":false,"isWrittenOff":false,"isClosed":true,"internalAccountType":"personal","isWrittenOffBasedOnLatestPayment":false,"isDelinquent":false,"isClosedAndNotWrittenOff":true,"noOfMonthsBtwReportDateAndDisbursalDate":4,"maxDpdInLast1Month":0,"maxDpdInLast3Months":0,"maxDpdInLast6Months":0,"maxDpdInLast9Months":0,"maxDpdInLast12Months":0,"noOfTimesDefaulted":0,"isDpdAtLeastOnce":false,"isDpdThirtyAtLeastOnce":false,"isDpdSixtyAtLeastOnce":false,"isDpdNinetyAtLeastOnce":false,"noOfDpdThirtyInLast3Months":0,"noOfDpdThirtyInLast6Months":0,"noOfDpdThirtyInLast9Months":0,"noOfDpdThirtyInLast12Months":0,"noOfDpdThirtyInLast24Months":0,"noOfDpdSixtyInLast3Months":0,"noOfDpdSixtyInLast6Months":0,"noOfDpdSixtyInLast9Months":0,"noOfDpdSixtyInLast12Months":0,"noOfDpdSixtyInLast24Months":0,"noOfDpdOneInLast3Months":0},{"accountNumber":"MK80A56105ID29308919","accountType":"Personal Loan","dateReported":"31-03-2022","accountStatus":"Closed","disbursedAmount":"1,000","disbursedDate":"29-01-2022","lastPaymentDate":"02-03-2022","closeDate":null,"installmentAmount":null,"interestRate":null,"overdueAmount":"0","writeoffAmount":"0","currentBalance":"0","creditLimit":null,"accountRemarks":null,"frequency":null,"combinedPaymentHistory":"Mar:2022,000/XXX|Feb:2022,002/XXX|Jan:2022,002/XXX|","cashLimit":null,"actualPayment":null,"repaymentTenure":null,"disbursedAmountInt":1000,"currentBalanceInt":0,"overdueAmtInt":0,"writeoffAmountInt":0,"creditLimitInt":0,"latestMonthPayment":{"month":"Mar","year":"2022","dpd":0,"assetClassificationCode":"XXX","distanceFromReportDate":3},"totalPayments":3,"installmentAmountInt":33,"isActive":false,"isWrittenOff":false,"isClosed":true,"internalAccountType":"personal","isWrittenOffBasedOnLatestPayment":false,"isDelinquent":false,"isClosedAndNotWrittenOff":true,"noOfMonthsBtwReportDateAndDisbursalDate":4,"maxDpdInLast1Month":0,"maxDpdInLast3Months":0,"maxDpdInLast6Months":2,"maxDpdInLast9Months":2,"maxDpdInLast12Months":2,"noOfTimesDefaulted":2,"isDpdAtLeastOnce":true,"isDpdThirtyAtLeastOnce":false,"isDpdSixtyAtLeastOnce":false,"isDpdNinetyAtLeastOnce":false,"noOfDpdThirtyInLast3Months":0,"noOfDpdThirtyInLast6Months":0,"noOfDpdThirtyInLast9Months":0,"noOfDpdThirtyInLast12Months":0,"noOfDpdThirtyInLast24Months":0,"noOfDpdSixtyInLast3Months":0,"noOfDpdSixtyInLast6Months":0,"noOfDpdSixtyInLast9Months":0,"noOfDpdSixtyInLast12Months":0,"noOfDpdSixtyInLast24Months":0,"noOfDpdOneInLast3Months":0},{"accountNumber":"MK335862F2ID31145837","accountType":"Personal Loan","dateReported":"30-04-2022","accountStatus":"Closed","disbursedAmount":"1,000","disbursedDate":"02-03-2022","lastPaymentDate":"05-04-2022","closeDate":null,"installmentAmount":null,"interestRate":null,"overdueAmount":"0","writeoffAmount":"0","currentBalance":"0","creditLimit":null,"accountRemarks":null,"frequency":null,"combinedPaymentHistory":"Apr:2022,000/XXX|Mar:2022,004/XXX|","cashLimit":null,"actualPayment":null,"repaymentTenure":null,"disbursedAmountInt":1000,"currentBalanceInt":0,"overdueAmtInt":0,"writeoffAmountInt":0,"creditLimitInt":0,"latestMonthPayment":{"month":"Apr","year":"2022","dpd":0,"assetClassificationCode":"XXX","distanceFromReportDate":2},"totalPayments":2,"installmentAmountInt":33,"isActive":false,"isWrittenOff":false,"isClosed":true,"internalAccountType":"personal","isWrittenOffBasedOnLatestPayment":false,"isDelinquent":false,"isClosedAndNotWrittenOff":true,"noOfMonthsBtwReportDateAndDisbursalDate":3,"maxDpdInLast1Month":0,"maxDpdInLast3Months":4,"maxDpdInLast6Months":4,"maxDpdInLast9Months":4,"maxDpdInLast12Months":4,"noOfTimesDefaulted":1,"isDpdAtLeastOnce":true,"isDpdThirtyAtLeastOnce":false,"isDpdSixtyAtLeastOnce":false,"isDpdNinetyAtLeastOnce":false,"noOfDpdThirtyInLast3Months":0,"noOfDpdThirtyInLast6Months":0,"noOfDpdThirtyInLast9Months":0,"noOfDpdThirtyInLast12Months":0,"noOfDpdThirtyInLast24Months":0,"noOfDpdSixtyInLast3Months":0,"noOfDpdSixtyInLast6Months":0,"noOfDpdSixtyInLast9Months":0,"noOfDpdSixtyInLast12Months":0,"noOfDpdSixtyInLast24Months":0,"noOfDpdOneInLast3Months":1},{"accountNumber":"MK7B5A6168ID26191884","accountType":"Personal Loan","dateReported":"31-12-2021","accountStatus":"Closed","disbursedAmount":"1,000","disbursedDate":"29-11-2021","lastPaymentDate":"19-12-2021","closeDate":null,"installmentAmount":null,"interestRate":null,"overdueAmount":"0","writeoffAmount":"0","currentBalance":"0","creditLimit":null,"accountRemarks":null,"frequency":null,"combinedPaymentHistory":"Dec:2021,000/XXX|Nov:2021,XXX/STD|","cashLimit":null,"actualPayment":null,"repaymentTenure":null,"disbursedAmountInt":1000,"currentBalanceInt":0,"overdueAmtInt":0,"writeoffAmountInt":0,"creditLimitInt":0,"latestMonthPayment":{"month":"Dec","year":"2021","dpd":0,"assetClassificationCode":"XXX","distanceFromReportDate":6},"totalPayments":2,"installmentAmountInt":33,"isActive":false,"isWrittenOff":false,"isClosed":true,"internalAccountType":"personal","isWrittenOffBasedOnLatestPayment":false,"isDelinquent":false,"isClosedAndNotWrittenOff":true,"noOfMonthsBtwReportDateAndDisbursalDate":6,"maxDpdInLast1Month":0,"maxDpdInLast3Months":0,"maxDpdInLast6Months":0,"maxDpdInLast9Months":0,"maxDpdInLast12Months":0,"noOfTimesDefaulted":0,"isDpdAtLeastOnce":false,"isDpdThirtyAtLeastOnce":false,"isDpdSixtyAtLeastOnce":false,"isDpdNinetyAtLeastOnce":false,"noOfDpdThirtyInLast3Months":0,"noOfDpdThirtyInLast6Months":0,"noOfDpdThirtyInLast9Months":0,"noOfDpdThirtyInLast12Months":0,"noOfDpdThirtyInLast24Months":0,"noOfDpdSixtyInLast3Months":0,"noOfDpdSixtyInLast6Months":0,"noOfDpdSixtyInLast9Months":0,"noOfDpdSixtyInLast12Months":0,"noOfDpdSixtyInLast24Months":0,"noOfDpdOneInLast3Months":0},{"accountNumber":"MKCB9C60ECID19297680","accountType":"Personal Loan","dateReported":"31-08-2021","accountStatus":"Closed","disbursedAmount":"2,000","disbursedDate":"15-06-2021","lastPaymentDate":"13-08-2021","closeDate":null,"installmentAmount":null,"interestRate":null,"overdueAmount":"0","writeoffAmount":"0","currentBalance":"0","creditLimit":null,"accountRemarks":null,"frequency":null,"combinedPaymentHistory":"Aug:2021,000/XXX|Jul:2021,XXX/STD|","cashLimit":null,"actualPayment":null,"repaymentTenure":null,"disbursedAmountInt":2000,"currentBalanceInt":0,"overdueAmtInt":0,"writeoffAmountInt":0,"creditLimitInt":0,"latestMonthPayment":{"month":"Aug","year":"2021","dpd":0,"assetClassificationCode":"XXX","distanceFromReportDate":10},"totalPayments":2,"installmentAmountInt":66,"isActive":false,"isWrittenOff":false,"isClosed":true,"internalAccountType":"personal","isWrittenOffBasedOnLatestPayment":false,"isDelinquent":false,"isClosedAndNotWrittenOff":true,"noOfMonthsBtwReportDateAndDisbursalDate":11,"maxDpdInLast1Month":0,"maxDpdInLast3Months":0,"maxDpdInLast6Months":0,"maxDpdInLast9Months":0,"maxDpdInLast12Months":0,"noOfTimesDefaulted":0,"isDpdAtLeastOnce":false,"isDpdThirtyAtLeastOnce":false,"isDpdSixtyAtLeastOnce":false,"isDpdNinetyAtLeastOnce":false,"noOfDpdThirtyInLast3Months":0,"noOfDpdThirtyInLast6Months":0,"noOfDpdThirtyInLast9Months":0,"noOfDpdThirtyInLast12Months":0,"noOfDpdThirtyInLast24Months":0,"noOfDpdSixtyInLast3Months":0,"noOfDpdSixtyInLast6Months":0,"noOfDpdSixtyInLast9Months":0,"noOfDpdSixtyInLast12Months":0,"noOfDpdSixtyInLast24Months":0,"noOfDpdOneInLast3Months":0},{"accountNumber":"MK5CDF6113ID28657623","accountType":"Personal Loan","dateReported":"28-02-2022","accountStatus":"Closed","disbursedAmount":"1,000","disbursedDate":"17-01-2022","lastPaymentDate":"17-02-2022","closeDate":null,"installmentAmount":null,"interestRate":null,"overdueAmount":"0","writeoffAmount":"0","currentBalance":"0","creditLimit":null,"accountRemarks":null,"frequency":null,"combinedPaymentHistory":"Feb:2022,000/XXX|","cashLimit":null,"actualPayment":null,"repaymentTenure":null,"disbursedAmountInt":1000,"currentBalanceInt":0,"overdueAmtInt":0,"writeoffAmountInt":0,"creditLimitInt":0,"latestMonthPayment":{"month":"Feb","year":"2022","dpd":0,"assetClassificationCode":"XXX","distanceFromReportDate":4},"totalPayments":1,"installmentAmountInt":33,"isActive":false,"isWrittenOff":false,"isClosed":true,"internalAccountType":"personal","isWrittenOffBasedOnLatestPayment":false,"isDelinquent":false,"isClosedAndNotWrittenOff":true,"noOfMonthsBtwReportDateAndDisbursalDate":4,"maxDpdInLast1Month":0,"maxDpdInLast3Months":0,"maxDpdInLast6Months":0,"maxDpdInLast9Months":0,"maxDpdInLast12Months":0,"noOfTimesDefaulted":0,"isDpdAtLeastOnce":false,"isDpdThirtyAtLeastOnce":false,"isDpdSixtyAtLeastOnce":false,"isDpdNinetyAtLeastOnce":false,"noOfDpdThirtyInLast3Months":0,"noOfDpdThirtyInLast6Months":0,"noOfDpdThirtyInLast9Months":0,"noOfDpdThirtyInLast12Months":0,"noOfDpdThirtyInLast24Months":0,"noOfDpdSixtyInLast3Months":0,"noOfDpdSixtyInLast6Months":0,"noOfDpdSixtyInLast9Months":0,"noOfDpdSixtyInLast12Months":0,"noOfDpdSixtyInLast24Months":0,"noOfDpdOneInLast3Months":0},{"accountNumber":"ATPL319637S320032","accountType":"Personal Loan","dateReported":"04-05-2021","accountStatus":"Active","disbursedAmount":"1,000","disbursedDate":"27-04-2021","lastPaymentDate":null,"closeDate":null,"installmentAmount":"550","interestRate":null,"overdueAmount":"0","writeoffAmount":"0","currentBalance":"500","creditLimit":null,"accountRemarks":null,"frequency":null,"combinedPaymentHistory":"May:2021,000/XXX|","cashLimit":null,"actualPayment":null,"repaymentTenure":null,"disbursedAmountInt":1000,"currentBalanceInt":500,"overdueAmtInt":0,"writeoffAmountInt":0,"creditLimitInt":0,"latestMonthPayment":{"month":"May","year":"2021","dpd":0,"assetClassificationCode":"XXX","distanceFromReportDate":13},"totalPayments":1,"installmentAmountInt":550,"isActive":false,"isWrittenOff":false,"isClosed":true,"internalAccountType":"personal","isWrittenOffBasedOnLatestPayment":false,"isDelinquent":false,"isClosedAndNotWrittenOff":true,"noOfMonthsBtwReportDateAndDisbursalDate":13,"maxDpdInLast1Month":0,"maxDpdInLast3Months":0,"maxDpdInLast6Months":0,"maxDpdInLast9Months":0,"maxDpdInLast12Months":0,"noOfTimesDefaulted":0,"isDpdAtLeastOnce":false,"isDpdThirtyAtLeastOnce":false,"isDpdSixtyAtLeastOnce":false,"isDpdNinetyAtLeastOnce":false,"noOfDpdThirtyInLast3Months":0,"noOfDpdThirtyInLast6Months":0,"noOfDpdThirtyInLast9Months":0,"noOfDpdThirtyInLast12Months":0,"noOfDpdThirtyInLast24Months":0,"noOfDpdSixtyInLast3Months":0,"noOfDpdSixtyInLast6Months":0,"noOfDpdSixtyInLast9Months":0,"noOfDpdSixtyInLast12Months":0,"noOfDpdSixtyInLast24Months":0,"noOfDpdOneInLast3Months":0},{"accountNumber":"PYTMPPABFL115831881067876","accountType":"Other","dateReported":"30-04-2022","accountStatus":"Active","disbursedAmount":"500","disbursedDate":"05-01-2022","lastPaymentDate":"02-04-2022","closeDate":null,"installmentAmount":"0","interestRate":null,"overdueAmount":"0","writeoffAmount":"0","currentBalance":"493","creditLimit":null,"accountRemarks":null,"frequency":null,"combinedPaymentHistory":"Apr:2022,000/STD|Mar:2022,000/STD|Feb:2022,000/STD|Jan:2022,000/STD|","cashLimit":null,"actualPayment":null,"repaymentTenure":null,"disbursedAmountInt":500,"currentBalanceInt":493,"overdueAmtInt":0,"writeoffAmountInt":0,"creditLimitInt":0,"latestMonthPayment":{"month":"Apr","year":"2022","dpd":0,"assetClassificationCode":"STD","distanceFromReportDate":2},"totalPayments":4,"installmentAmountInt":17,"isActive":true,"isWrittenOff":false,"isClosed":false,"internalAccountType":"other","isWrittenOffBasedOnLatestPayment":false,"isDelinquent":false,"isClosedAndNotWrittenOff":false,"noOfMonthsBtwReportDateAndDisbursalDate":5,"maxDpdInLast1Month":0,"maxDpdInLast3Months":0,"maxDpdInLast6Months":0,"maxDpdInLast9Months":0,"maxDpdInLast12Months":0,"noOfTimesDefaulted":0,"isDpdAtLeastOnce":false,"isDpdThirtyAtLeastOnce":false,"isDpdSixtyAtLeastOnce":false,"isDpdNinetyAtLeastOnce":false,"noOfDpdThirtyInLast3Months":0,"noOfDpdThirtyInLast6Months":0,"noOfDpdThirtyInLast9Months":0,"noOfDpdThirtyInLast12Months":0,"noOfDpdThirtyInLast24Months":0,"noOfDpdSixtyInLast3Months":0,"noOfDpdSixtyInLast6Months":0,"noOfDpdSixtyInLast9Months":0,"noOfDpdSixtyInLast12Months":0,"noOfDpdSixtyInLast24Months":0,"noOfDpdOneInLast3Months":0},{"accountNumber":"MKB41862AFID31145673","accountType":"Personal Loan","dateReported":"30-04-2022","accountStatus":"Closed","disbursedAmount":"1,000","disbursedDate":"02-03-2022","lastPaymentDate":"05-04-2022","closeDate":null,"installmentAmount":null,"interestRate":null,"overdueAmount":"0","writeoffAmount":"0","currentBalance":"0","creditLimit":null,"accountRemarks":null,"frequency":null,"combinedPaymentHistory":"Apr:2022,000/XXX|Mar:2022,004/XXX|","cashLimit":null,"actualPayment":null,"repaymentTenure":null,"disbursedAmountInt":1000,"currentBalanceInt":0,"overdueAmtInt":0,"writeoffAmountInt":0,"creditLimitInt":0,"latestMonthPayment":{"month":"Apr","year":"2022","dpd":0,"assetClassificationCode":"XXX","distanceFromReportDate":2},"totalPayments":2,"installmentAmountInt":33,"isActive":false,"isWrittenOff":false,"isClosed":true,"internalAccountType":"personal","isWrittenOffBasedOnLatestPayment":false,"isDelinquent":false,"isClosedAndNotWrittenOff":true,"noOfMonthsBtwReportDateAndDisbursalDate":3,"maxDpdInLast1Month":0,"maxDpdInLast3Months":4,"maxDpdInLast6Months":4,"maxDpdInLast9Months":4,"maxDpdInLast12Months":4,"noOfTimesDefaulted":1,"isDpdAtLeastOnce":true,"isDpdThirtyAtLeastOnce":false,"isDpdSixtyAtLeastOnce":false,"isDpdNinetyAtLeastOnce":false,"noOfDpdThirtyInLast3Months":0,"noOfDpdThirtyInLast6Months":0,"noOfDpdThirtyInLast9Months":0,"noOfDpdThirtyInLast12Months":0,"noOfDpdThirtyInLast24Months":0,"noOfDpdSixtyInLast3Months":0,"noOfDpdSixtyInLast6Months":0,"noOfDpdSixtyInLast9Months":0,"noOfDpdSixtyInLast12Months":0,"noOfDpdSixtyInLast24Months":0,"noOfDpdOneInLast3Months":1},{"accountNumber":"MK6F326265ID32673933","accountType":"Personal Loan","dateReported":"30-04-2022","accountStatus":"Active","disbursedAmount":"2,000","disbursedDate":"27-03-2022","lastPaymentDate":null,"closeDate":null,"installmentAmount":null,"interestRate":null,"overdueAmount":null,"writeoffAmount":"0","currentBalance":"2,200","creditLimit":null,"accountRemarks":null,"frequency":null,"combinedPaymentHistory":"Apr:2022,XXX/STD|Mar:2022,XXX/STD|","cashLimit":null,"actualPayment":null,"repaymentTenure":null,"disbursedAmountInt":2000,"currentBalanceInt":2200,"overdueAmtInt":0,"writeoffAmountInt":0,"creditLimitInt":0,"latestMonthPayment":{"month":"Apr","year":"2022","dpd":0,"assetClassificationCode":"STD","distanceFromReportDate":2},"totalPayments":2,"installmentAmountInt":66,"isActive":true,"isWrittenOff":false,"isClosed":false,"internalAccountType":"personal","isWrittenOffBasedOnLatestPayment":false,"isDelinquent":false,"isClosedAndNotWrittenOff":false,"noOfMonthsBtwReportDateAndDisbursalDate":2,"maxDpdInLast1Month":0,"maxDpdInLast3Months":0,"maxDpdInLast6Months":0,"maxDpdInLast9Months":0,"maxDpdInLast12Months":0,"noOfTimesDefaulted":0,"isDpdAtLeastOnce":false,"isDpdThirtyAtLeastOnce":false,"isDpdSixtyAtLeastOnce":false,"isDpdNinetyAtLeastOnce":false,"noOfDpdThirtyInLast3Months":0,"noOfDpdThirtyInLast6Months":0,"noOfDpdThirtyInLast9Months":0,"noOfDpdThirtyInLast12Months":0,"noOfDpdThirtyInLast24Months":0,"noOfDpdSixtyInLast3Months":0,"noOfDpdSixtyInLast6Months":0,"noOfDpdSixtyInLast9Months":0,"noOfDpdSixtyInLast12Months":0,"noOfDpdSixtyInLast24Months":0,"noOfDpdOneInLast3Months":0},{"accountNumber":"MK69CB6052ID19572474","accountType":"Personal Loan","dateReported":"31-08-2021","accountStatus":"Closed","disbursedAmount":"1,000","disbursedDate":"24-06-2021","lastPaymentDate":"24-08-2021","closeDate":null,"installmentAmount":null,"interestRate":null,"overdueAmount":"0","writeoffAmount":"0","currentBalance":"0","creditLimit":null,"accountRemarks":null,"frequency":null,"combinedPaymentHistory":"Aug:2021,000/XXX|Jul:2021,XXX/STD|","cashLimit":null,"actualPayment":null,"repaymentTenure":null,"disbursedAmountInt":1000,"currentBalanceInt":0,"overdueAmtInt":0,"writeoffAmountInt":0,"creditLimitInt":0,"latestMonthPayment":{"month":"Aug","year":"2021","dpd":0,"assetClassificationCode":"XXX","distanceFromReportDate":10},"totalPayments":2,"installmentAmountInt":33,"isActive":false,"isWrittenOff":false,"isClosed":true,"internalAccountType":"personal","isWrittenOffBasedOnLatestPayment":false,"isDelinquent":false,"isClosedAndNotWrittenOff":true,"noOfMonthsBtwReportDateAndDisbursalDate":11,"maxDpdInLast1Month":0,"maxDpdInLast3Months":0,"maxDpdInLast6Months":0,"maxDpdInLast9Months":0,"maxDpdInLast12Months":0,"noOfTimesDefaulted":0,"isDpdAtLeastOnce":false,"isDpdThirtyAtLeastOnce":false,"isDpdSixtyAtLeastOnce":false,"isDpdNinetyAtLeastOnce":false,"noOfDpdThirtyInLast3Months":0,"noOfDpdThirtyInLast6Months":0,"noOfDpdThirtyInLast9Months":0,"noOfDpdThirtyInLast12Months":0,"noOfDpdThirtyInLast24Months":0,"noOfDpdSixtyInLast3Months":0,"noOfDpdSixtyInLast6Months":0,"noOfDpdSixtyInLast9Months":0,"noOfDpdSixtyInLast12Months":0,"noOfDpdSixtyInLast24Months":0,"noOfDpdOneInLast3Months":0},{"accountNumber":"MK8C616239ID32673905","accountType":"Personal Loan","dateReported":"30-04-2022","accountStatus":"Active","disbursedAmount":"2,000","disbursedDate":"27-03-2022","lastPaymentDate":null,"closeDate":null,"installmentAmount":null,"interestRate":null,"overdueAmount":null,"writeoffAmount":"0","currentBalance":"2,200","creditLimit":null,"accountRemarks":null,"frequency":null,"combinedPaymentHistory":"Apr:2022,XXX/STD|Mar:2022,XXX/STD|","cashLimit":null,"actualPayment":null,"repaymentTenure":null,"disbursedAmountInt":2000,"currentBalanceInt":2200,"overdueAmtInt":0,"writeoffAmountInt":0,"creditLimitInt":0,"latestMonthPayment":{"month":"Apr","year":"2022","dpd":0,"assetClassificationCode":"STD","distanceFromReportDate":2},"totalPayments":2,"installmentAmountInt":66,"isActive":true,"isWrittenOff":false,"isClosed":false,"internalAccountType":"personal","isWrittenOffBasedOnLatestPayment":false,"isDelinquent":false,"isClosedAndNotWrittenOff":false,"noOfMonthsBtwReportDateAndDisbursalDate":2,"maxDpdInLast1Month":0,"maxDpdInLast3Months":0,"maxDpdInLast6Months":0,"maxDpdInLast9Months":0,"maxDpdInLast12Months":0,"noOfTimesDefaulted":0,"isDpdAtLeastOnce":false,"isDpdThirtyAtLeastOnce":false,"isDpdSixtyAtLeastOnce":false,"isDpdNinetyAtLeastOnce":false,"noOfDpdThirtyInLast3Months":0,"noOfDpdThirtyInLast6Months":0,"noOfDpdThirtyInLast9Months":0,"noOfDpdThirtyInLast12Months":0,"noOfDpdThirtyInLast24Months":0,"noOfDpdSixtyInLast3Months":0,"noOfDpdSixtyInLast6Months":0,"noOfDpdSixtyInLast9Months":0,"noOfDpdSixtyInLast12Months":0,"noOfDpdSixtyInLast24Months":0,"noOfDpdOneInLast3Months":0},{"accountNumber":"DMI0007097607","accountType":"Consumer Loan","dateReported":"30-04-2022","accountStatus":"Active","disbursedAmount":"35,000","disbursedDate":"23-06-2020","lastPaymentDate":"05-04-2022","closeDate":null,"installmentAmount":null,"interestRate":null,"overdueAmount":"0","writeoffAmount":"0","currentBalance":"9,102","creditLimit":"35,000","accountRemarks":null,"frequency":null,"combinedPaymentHistory":"Apr:2022,000/STD|Mar:2022,000/STD|Feb:2022,000/STD|Jan:2022,000/STD|Dec:2021,000/STD|Nov:2021,000/STD|Oct:2021,000/STD|Sep:2021,000/STD|Aug:2021,000/STD|Jul:2021,000/STD|Jun:2021,000/STD|May:2021,000/STD|Apr:2021,000/STD|Mar:2021,000/STD|Feb:2021,000/STD|Jan:2021,000/STD|Dec:2020,000/STD|Nov:2020,000/STD|Oct:2020,000/STD|Sep:2020,000/STD|Aug:2020,DDD/DDD|Jul:2020,000/STD|","cashLimit":"35,000","actualPayment":null,"repaymentTenure":null,"disbursedAmountInt":35000,"currentBalanceInt":9102,"overdueAmtInt":0,"writeoffAmountInt":0,"creditLimitInt":35000,"latestMonthPayment":{"month":"Apr","year":"2022","dpd":0,"assetClassificationCode":"STD","distanceFromReportDate":2},"totalPayments":22,"installmentAmountInt":2134,"isActive":true,"isWrittenOff":false,"isClosed":false,"internalAccountType":"consumer","isWrittenOffBasedOnLatestPayment":false,"isDelinquent":false,"isClosedAndNotWrittenOff":false,"noOfMonthsBtwReportDateAndDisbursalDate":23,"maxDpdInLast1Month":0,"maxDpdInLast3Months":0,"maxDpdInLast6Months":0,"maxDpdInLast9Months":0,"maxDpdInLast12Months":0,"noOfTimesDefaulted":0,"isDpdAtLeastOnce":false,"isDpdThirtyAtLeastOnce":false,"isDpdSixtyAtLeastOnce":false,"isDpdNinetyAtLeastOnce":false,"noOfDpdThirtyInLast3Months":0,"noOfDpdThirtyInLast6Months":0,"noOfDpdThirtyInLast9Months":0,"noOfDpdThirtyInLast12Months":0,"noOfDpdThirtyInLast24Months":0,"noOfDpdSixtyInLast3Months":0,"noOfDpdSixtyInLast6Months":0,"noOfDpdSixtyInLast9Months":0,"noOfDpdSixtyInLast12Months":0,"noOfDpdSixtyInLast24Months":0,"noOfDpdOneInLast3Months":0},{"accountNumber":"ATPL319637S320032","accountType":"Personal Loan","dateReported":"30-04-2022","accountStatus":"Closed","disbursedAmount":"5,500","disbursedDate":"27-04-2021","lastPaymentDate":"21-05-2021","closeDate":null,"installmentAmount":"550","interestRate":null,"overdueAmount":"0","writeoffAmount":"0","currentBalance":"0","creditLimit":null,"accountRemarks":null,"frequency":null,"combinedPaymentHistory":"","cashLimit":null,"actualPayment":null,"repaymentTenure":null,"disbursedAmountInt":5500,"currentBalanceInt":0,"overdueAmtInt":0,"writeoffAmountInt":0,"creditLimitInt":0,"latestMonthPayment":{},"totalPayments":0,"installmentAmountInt":550,"isActive":false,"isWrittenOff":false,"isClosed":true,"internalAccountType":"personal","isWrittenOffBasedOnLatestPayment":false,"isDelinquent":false,"isClosedAndNotWrittenOff":true,"noOfMonthsBtwReportDateAndDisbursalDate":13,"maxDpdInLast1Month":0,"maxDpdInLast3Months":0,"maxDpdInLast6Months":0,"maxDpdInLast9Months":0,"maxDpdInLast12Months":0,"noOfTimesDefaulted":0,"isDpdAtLeastOnce":false,"isDpdThirtyAtLeastOnce":false,"isDpdSixtyAtLeastOnce":false,"isDpdNinetyAtLeastOnce":false,"noOfDpdThirtyInLast3Months":0,"noOfDpdThirtyInLast6Months":0,"noOfDpdThirtyInLast9Months":0,"noOfDpdThirtyInLast12Months":0,"noOfDpdThirtyInLast24Months":0,"noOfDpdSixtyInLast3Months":0,"noOfDpdSixtyInLast6Months":0,"noOfDpdSixtyInLast9Months":0,"noOfDpdSixtyInLast12Months":0,"noOfDpdSixtyInLast24Months":0,"noOfDpdOneInLast3Months":0},{"accountNumber":"MK4DBB61C3ID26836463","accountType":"Personal Loan","dateReported":"31-12-2021","accountStatus":"Closed","disbursedAmount":"500","disbursedDate":"12-12-2021","lastPaymentDate":"11-01-2022","closeDate":null,"installmentAmount":null,"interestRate":null,"overdueAmount":null,"writeoffAmount":"0","currentBalance":"525","creditLimit":null,"accountRemarks":null,"frequency":null,"combinedPaymentHistory":"Dec:2021,XXX/STD|","cashLimit":null,"actualPayment":null,"repaymentTenure":null,"disbursedAmountInt":500,"currentBalanceInt":525,"overdueAmtInt":0,"writeoffAmountInt":0,"creditLimitInt":0,"latestMonthPayment":{"month":"Dec","year":"2021","dpd":0,"assetClassificationCode":"STD","distanceFromReportDate":6},"totalPayments":1,"installmentAmountInt":17,"isActive":false,"isWrittenOff":false,"isClosed":true,"internalAccountType":"personal","isWrittenOffBasedOnLatestPayment":false,"isDelinquent":false,"isClosedAndNotWrittenOff":true,"noOfMonthsBtwReportDateAndDisbursalDate":5,"maxDpdInLast1Month":0,"maxDpdInLast3Months":0,"maxDpdInLast6Months":0,"maxDpdInLast9Months":0,"maxDpdInLast12Months":0,"noOfTimesDefaulted":0,"isDpdAtLeastOnce":false,"isDpdThirtyAtLeastOnce":false,"isDpdSixtyAtLeastOnce":false,"isDpdNinetyAtLeastOnce":false,"noOfDpdThirtyInLast3Months":0,"noOfDpdThirtyInLast6Months":0,"noOfDpdThirtyInLast9Months":0,"noOfDpdThirtyInLast12Months":0,"noOfDpdThirtyInLast24Months":0,"noOfDpdSixtyInLast3Months":0,"noOfDpdSixtyInLast6Months":0,"noOfDpdSixtyInLast9Months":0,"noOfDpdSixtyInLast12Months":0,"noOfDpdSixtyInLast24Months":0,"noOfDpdOneInLast3Months":0},{"accountNumber":"MK7CD861CCID29111814","accountType":"Personal Loan","dateReported":"28-02-2022","accountStatus":"Closed","disbursedAmount":"1,000","disbursedDate":"25-01-2022","lastPaymentDate":"23-02-2022","closeDate":null,"installmentAmount":null,"interestRate":null,"overdueAmount":"0","writeoffAmount":"0","currentBalance":"0","creditLimit":null,"accountRemarks":null,"frequency":null,"combinedPaymentHistory":"Feb:2022,000/XXX|","cashLimit":null,"actualPayment":null,"repaymentTenure":null,"disbursedAmountInt":1000,"currentBalanceInt":0,"overdueAmtInt":0,"writeoffAmountInt":0,"creditLimitInt":0,"latestMonthPayment":{"month":"Feb","year":"2022","dpd":0,"assetClassificationCode":"XXX","distanceFromReportDate":4},"totalPayments":1,"installmentAmountInt":33,"isActive":false,"isWrittenOff":false,"isClosed":true,"internalAccountType":"personal","isWrittenOffBasedOnLatestPayment":false,"isDelinquent":false,"isClosedAndNotWrittenOff":true,"noOfMonthsBtwReportDateAndDisbursalDate":4,"maxDpdInLast1Month":0,"maxDpdInLast3Months":0,"maxDpdInLast6Months":0,"maxDpdInLast9Months":0,"maxDpdInLast12Months":0,"noOfTimesDefaulted":0,"isDpdAtLeastOnce":false,"isDpdThirtyAtLeastOnce":false,"isDpdSixtyAtLeastOnce":false,"isDpdNinetyAtLeastOnce":false,"noOfDpdThirtyInLast3Months":0,"noOfDpdThirtyInLast6Months":0,"noOfDpdThirtyInLast9Months":0,"noOfDpdThirtyInLast12Months":0,"noOfDpdThirtyInLast24Months":0,"noOfDpdSixtyInLast3Months":0,"noOfDpdSixtyInLast6Months":0,"noOfDpdSixtyInLast9Months":0,"noOfDpdSixtyInLast12Months":0,"noOfDpdSixtyInLast24Months":0,"noOfDpdOneInLast3Months":0},{"accountNumber":"MK564561BDID27047940","accountType":"Personal Loan","dateReported":"31-12-2021","accountStatus":"Closed","disbursedAmount":"500","disbursedDate":"16-12-2021","lastPaymentDate":"15-01-2022","closeDate":null,"installmentAmount":null,"interestRate":null,"overdueAmount":null,"writeoffAmount":"0","currentBalance":"525","creditLimit":null,"accountRemarks":null,"frequency":null,"combinedPaymentHistory":"Dec:2021,XXX/STD|","cashLimit":null,"actualPayment":null,"repaymentTenure":null,"disbursedAmountInt":500,"currentBalanceInt":525,"overdueAmtInt":0,"writeoffAmountInt":0,"creditLimitInt":0,"latestMonthPayment":{"month":"Dec","year":"2021","dpd":0,"assetClassificationCode":"STD","distanceFromReportDate":6},"totalPayments":1,"installmentAmountInt":17,"isActive":false,"isWrittenOff":false,"isClosed":true,"internalAccountType":"personal","isWrittenOffBasedOnLatestPayment":false,"isDelinquent":false,"isClosedAndNotWrittenOff":true,"noOfMonthsBtwReportDateAndDisbursalDate":5,"maxDpdInLast1Month":0,"maxDpdInLast3Months":0,"maxDpdInLast6Months":0,"maxDpdInLast9Months":0,"maxDpdInLast12Months":0,"noOfTimesDefaulted":0,"isDpdAtLeastOnce":false,"isDpdThirtyAtLeastOnce":false,"isDpdSixtyAtLeastOnce":false,"isDpdNinetyAtLeastOnce":false,"noOfDpdThirtyInLast3Months":0,"noOfDpdThirtyInLast6Months":0,"noOfDpdThirtyInLast9Months":0,"noOfDpdThirtyInLast12Months":0,"noOfDpdThirtyInLast24Months":0,"noOfDpdSixtyInLast3Months":0,"noOfDpdSixtyInLast6Months":0,"noOfDpdSixtyInLast9Months":0,"noOfDpdSixtyInLast12Months":0,"noOfDpdSixtyInLast24Months":0,"noOfDpdOneInLast3Months":0},{"accountNumber":"MK7DB861EEID28273444","accountType":"Personal Loan","dateReported":"31-03-2022","accountStatus":"Closed","disbursedAmount":"2,000","disbursedDate":"10-01-2022","lastPaymentDate":"14-03-2022","closeDate":null,"installmentAmount":null,"interestRate":null,"overdueAmount":"0","writeoffAmount":"0","currentBalance":"0","creditLimit":null,"accountRemarks":null,"frequency":null,"combinedPaymentHistory":"Mar:2022,000/XXX|Feb:2022,XXX/STD|Jan:2022,XXX/STD|","cashLimit":null,"actualPayment":null,"repaymentTenure":null,"disbursedAmountInt":2000,"currentBalanceInt":0,"overdueAmtInt":0,"writeoffAmountInt":0,"creditLimitInt":0,"latestMonthPayment":{"month":"Mar","year":"2022","dpd":0,"assetClassificationCode":"XXX","distanceFromReportDate":3},"totalPayments":3,"installmentAmountInt":66,"isActive":false,"isWrittenOff":false,"isClosed":true,"internalAccountType":"personal","isWrittenOffBasedOnLatestPayment":false,"isDelinquent":false,"isClosedAndNotWrittenOff":true,"noOfMonthsBtwReportDateAndDisbursalDate":4,"maxDpdInLast1Month":0,"maxDpdInLast3Months":0,"maxDpdInLast6Months":0,"maxDpdInLast9Months":0,"maxDpdInLast12Months":0,"noOfTimesDefaulted":0,"isDpdAtLeastOnce":false,"isDpdThirtyAtLeastOnce":false,"isDpdSixtyAtLeastOnce":false,"isDpdNinetyAtLeastOnce":false,"noOfDpdThirtyInLast3Months":0,"noOfDpdThirtyInLast6Months":0,"noOfDpdThirtyInLast9Months":0,"noOfDpdThirtyInLast12Months":0,"noOfDpdThirtyInLast24Months":0,"noOfDpdSixtyInLast3Months":0,"noOfDpdSixtyInLast6Months":0,"noOfDpdSixtyInLast9Months":0,"noOfDpdSixtyInLast12Months":0,"noOfDpdSixtyInLast24Months":0,"noOfDpdOneInLast3Months":0},{"accountNumber":"MK3775627CID34641469","accountType":"Personal Loan","dateReported":"30-04-2022","accountStatus":"Active","disbursedAmount":"1,000","disbursedDate":"28-04-2022","lastPaymentDate":null,"closeDate":null,"installmentAmount":null,"interestRate":null,"overdueAmount":null,"writeoffAmount":"0","currentBalance":"1,031","creditLimit":null,"accountRemarks":null,"frequency":null,"combinedPaymentHistory":"Apr:2022,XXX/STD|","cashLimit":null,"actualPayment":null,"repaymentTenure":null,"disbursedAmountInt":1000,"currentBalanceInt":1031,"overdueAmtInt":0,"writeoffAmountInt":0,"creditLimitInt":0,"latestMonthPayment":{"month":"Apr","year":"2022","dpd":0,"assetClassificationCode":"STD","distanceFromReportDate":2},"totalPayments":1,"installmentAmountInt":33,"isActive":true,"isWrittenOff":false,"isClosed":false,"internalAccountType":"personal","isWrittenOffBasedOnLatestPayment":false,"isDelinquent":false,"isClosedAndNotWrittenOff":false,"noOfMonthsBtwReportDateAndDisbursalDate":1,"maxDpdInLast1Month":0,"maxDpdInLast3Months":0,"maxDpdInLast6Months":0,"maxDpdInLast9Months":0,"maxDpdInLast12Months":0,"noOfTimesDefaulted":0,"isDpdAtLeastOnce":false,"isDpdThirtyAtLeastOnce":false,"isDpdSixtyAtLeastOnce":false,"isDpdNinetyAtLeastOnce":false,"noOfDpdThirtyInLast3Months":0,"noOfDpdThirtyInLast6Months":0,"noOfDpdThirtyInLast9Months":0,"noOfDpdThirtyInLast12Months":0,"noOfDpdThirtyInLast24Months":0,"noOfDpdSixtyInLast3Months":0,"noOfDpdSixtyInLast6Months":0,"noOfDpdSixtyInLast9Months":0,"noOfDpdSixtyInLast12Months":0,"noOfDpdSixtyInLast24Months":0,"noOfDpdOneInLast3Months":0},{"accountNumber":"MK39766174ID29111762","accountType":"Personal Loan","dateReported":"31-03-2022","accountStatus":"Closed","disbursedAmount":"2,000","disbursedDate":"25-01-2022","lastPaymentDate":"28-03-2022","closeDate":null,"installmentAmount":null,"interestRate":null,"overdueAmount":"0","writeoffAmount":"0","currentBalance":"0","creditLimit":null,"accountRemarks":null,"frequency":null,"combinedPaymentHistory":"Mar:2022,000/XXX|Feb:2022,XXX/STD|Jan:2022,XXX/STD|","cashLimit":null,"actualPayment":null,"repaymentTenure":null,"disbursedAmountInt":2000,"currentBalanceInt":0,"overdueAmtInt":0,"writeoffAmountInt":0,"creditLimitInt":0,"latestMonthPayment":{"month":"Mar","year":"2022","dpd":0,"assetClassificationCode":"XXX","distanceFromReportDate":3},"totalPayments":3,"installmentAmountInt":66,"isActive":false,"isWrittenOff":false,"isClosed":true,"internalAccountType":"personal","isWrittenOffBasedOnLatestPayment":false,"isDelinquent":false,"isClosedAndNotWrittenOff":true,"noOfMonthsBtwReportDateAndDisbursalDate":4,"maxDpdInLast1Month":0,"maxDpdInLast3Months":0,"maxDpdInLast6Months":0,"maxDpdInLast9Months":0,"maxDpdInLast12Months":0,"noOfTimesDefaulted":0,"isDpdAtLeastOnce":false,"isDpdThirtyAtLeastOnce":false,"isDpdSixtyAtLeastOnce":false,"isDpdNinetyAtLeastOnce":false,"noOfDpdThirtyInLast3Months":0,"noOfDpdThirtyInLast6Months":0,"noOfDpdThirtyInLast9Months":0,"noOfDpdThirtyInLast12Months":0,"noOfDpdThirtyInLast24Months":0,"noOfDpdSixtyInLast3Months":0,"noOfDpdSixtyInLast6Months":0,"noOfDpdSixtyInLast9Months":0,"noOfDpdSixtyInLast12Months":0,"noOfDpdSixtyInLast24Months":0,"noOfDpdOneInLast3Months":0},{"accountNumber":"MK9AE96080ID19899624","accountType":"Personal Loan","dateReported":"31-08-2021","accountStatus":"Active","disbursedAmount":"500","disbursedDate":"03-07-2021","lastPaymentDate":null,"closeDate":null,"installmentAmount":null,"interestRate":null,"overdueAmount":null,"writeoffAmount":"0","currentBalance":"550","creditLimit":null,"accountRemarks":null,"frequency":null,"combinedPaymentHistory":"Aug:2021,XXX/STD|Jul:2021,XXX/STD|","cashLimit":null,"actualPayment":null,"repaymentTenure":null,"disbursedAmountInt":500,"currentBalanceInt":550,"overdueAmtInt":0,"writeoffAmountInt":0,"creditLimitInt":0,"latestMonthPayment":{"month":"Aug","year":"2021","dpd":0,"assetClassificationCode":"STD","distanceFromReportDate":10},"totalPayments":2,"installmentAmountInt":17,"isActive":false,"isWrittenOff":false,"isClosed":true,"internalAccountType":"personal","isWrittenOffBasedOnLatestPayment":false,"isDelinquent":false,"isClosedAndNotWrittenOff":true,"noOfMonthsBtwReportDateAndDisbursalDate":11,"maxDpdInLast1Month":0,"maxDpdInLast3Months":0,"maxDpdInLast6Months":0,"maxDpdInLast9Months":0,"maxDpdInLast12Months":0,"noOfTimesDefaulted":0,"isDpdAtLeastOnce":false,"isDpdThirtyAtLeastOnce":false,"isDpdSixtyAtLeastOnce":false,"isDpdNinetyAtLeastOnce":false,"noOfDpdThirtyInLast3Months":0,"noOfDpdThirtyInLast6Months":0,"noOfDpdThirtyInLast9Months":0,"noOfDpdThirtyInLast12Months":0,"noOfDpdThirtyInLast24Months":0,"noOfDpdSixtyInLast3Months":0,"noOfDpdSixtyInLast6Months":0,"noOfDpdSixtyInLast9Months":0,"noOfDpdSixtyInLast12Months":0,"noOfDpdSixtyInLast24Months":0,"noOfDpdOneInLast3Months":0},{"accountNumber":"MK958660B6ID19726818","accountType":"Personal Loan","dateReported":"31-08-2021","accountStatus":"Closed","disbursedAmount":"2,000","disbursedDate":"29-06-2021","lastPaymentDate":"13-08-2021","closeDate":null,"installmentAmount":null,"interestRate":null,"overdueAmount":"0","writeoffAmount":"0","currentBalance":"0","creditLimit":null,"accountRemarks":null,"frequency":null,"combinedPaymentHistory":"Aug:2021,000/XXX|Jul:2021,XXX/STD|","cashLimit":null,"actualPayment":null,"repaymentTenure":null,"disbursedAmountInt":2000,"currentBalanceInt":0,"overdueAmtInt":0,"writeoffAmountInt":0,"creditLimitInt":0,"latestMonthPayment":{"month":"Aug","year":"2021","dpd":0,"assetClassificationCode":"XXX","distanceFromReportDate":10},"totalPayments":2,"installmentAmountInt":66,"isActive":false,"isWrittenOff":false,"isClosed":true,"internalAccountType":"personal","isWrittenOffBasedOnLatestPayment":false,"isDelinquent":false,"isClosedAndNotWrittenOff":true,"noOfMonthsBtwReportDateAndDisbursalDate":11,"maxDpdInLast1Month":0,"maxDpdInLast3Months":0,"maxDpdInLast6Months":0,"maxDpdInLast9Months":0,"maxDpdInLast12Months":0,"noOfTimesDefaulted":0,"isDpdAtLeastOnce":false,"isDpdThirtyAtLeastOnce":false,"isDpdSixtyAtLeastOnce":false,"isDpdNinetyAtLeastOnce":false,"noOfDpdThirtyInLast3Months":0,"noOfDpdThirtyInLast6Months":0,"noOfDpdThirtyInLast9Months":0,"noOfDpdThirtyInLast12Months":0,"noOfDpdThirtyInLast24Months":0,"noOfDpdSixtyInLast3Months":0,"noOfDpdSixtyInLast6Months":0,"noOfDpdSixtyInLast9Months":0,"noOfDpdSixtyInLast12Months":0,"noOfDpdSixtyInLast24Months":0,"noOfDpdOneInLast3Months":0},{"accountNumber":"MKCC5F628CID34404471","accountType":"Personal Loan","dateReported":"30-04-2022","accountStatus":"Active","disbursedAmount":"2,000","disbursedDate":"23-04-2022","lastPaymentDate":null,"closeDate":null,"installmentAmount":null,"interestRate":null,"overdueAmount":null,"writeoffAmount":"0","currentBalance":"2,127","creditLimit":null,"accountRemarks":null,"frequency":null,"combinedPaymentHistory":"Apr:2022,XXX/STD|","cashLimit":null,"actualPayment":null,"repaymentTenure":null,"disbursedAmountInt":2000,"currentBalanceInt":2127,"overdueAmtInt":0,"writeoffAmountInt":0,"creditLimitInt":0,"latestMonthPayment":{"month":"Apr","year":"2022","dpd":0,"assetClassificationCode":"STD","distanceFromReportDate":2},"totalPayments":1,"installmentAmountInt":66,"isActive":true,"isWrittenOff":false,"isClosed":false,"internalAccountType":"personal","isWrittenOffBasedOnLatestPayment":false,"isDelinquent":false,"isClosedAndNotWrittenOff":false,"noOfMonthsBtwReportDateAndDisbursalDate":1,"maxDpdInLast1Month":0,"maxDpdInLast3Months":0,"maxDpdInLast6Months":0,"maxDpdInLast9Months":0,"maxDpdInLast12Months":0,"noOfTimesDefaulted":0,"isDpdAtLeastOnce":false,"isDpdThirtyAtLeastOnce":false,"isDpdSixtyAtLeastOnce":false,"isDpdNinetyAtLeastOnce":false,"noOfDpdThirtyInLast3Months":0,"noOfDpdThirtyInLast6Months":0,"noOfDpdThirtyInLast9Months":0,"noOfDpdThirtyInLast12Months":0,"noOfDpdThirtyInLast24Months":0,"noOfDpdSixtyInLast3Months":0,"noOfDpdSixtyInLast6Months":0,"noOfDpdSixtyInLast9Months":0,"noOfDpdSixtyInLast12Months":0,"noOfDpdSixtyInLast24Months":0,"noOfDpdOneInLast3Months":0},{"accountNumber":"MK8DBA60A2ID18687496","accountType":"Personal Loan","dateReported":"31-07-2021","accountStatus":"Closed","disbursedAmount":"2,000","disbursedDate":"28-05-2021","lastPaymentDate":"24-07-2021","closeDate":null,"installmentAmount":null,"interestRate":null,"overdueAmount":"0","writeoffAmount":"0","currentBalance":"0","creditLimit":null,"accountRemarks":null,"frequency":null,"combinedPaymentHistory":"Jul:2021,000/XXX|Jun:2021,XXX/XXX|","cashLimit":null,"actualPayment":null,"repaymentTenure":null,"disbursedAmountInt":2000,"currentBalanceInt":0,"overdueAmtInt":0,"writeoffAmountInt":0,"creditLimitInt":0,"latestMonthPayment":{"month":"Jul","year":"2021","dpd":0,"assetClassificationCode":"XXX","distanceFromReportDate":11},"totalPayments":2,"installmentAmountInt":66,"isActive":false,"isWrittenOff":false,"isClosed":true,"internalAccountType":"personal","isWrittenOffBasedOnLatestPayment":false,"isDelinquent":false,"isClosedAndNotWrittenOff":true,"noOfMonthsBtwReportDateAndDisbursalDate":12,"maxDpdInLast1Month":0,"maxDpdInLast3Months":0,"maxDpdInLast6Months":0,"maxDpdInLast9Months":0,"maxDpdInLast12Months":0,"noOfTimesDefaulted":0,"isDpdAtLeastOnce":false,"isDpdThirtyAtLeastOnce":false,"isDpdSixtyAtLeastOnce":false,"isDpdNinetyAtLeastOnce":false,"noOfDpdThirtyInLast3Months":0,"noOfDpdThirtyInLast6Months":0,"noOfDpdThirtyInLast9Months":0,"noOfDpdThirtyInLast12Months":0,"noOfDpdThirtyInLast24Months":0,"noOfDpdSixtyInLast3Months":0,"noOfDpdSixtyInLast6Months":0,"noOfDpdSixtyInLast9Months":0,"noOfDpdSixtyInLast12Months":0,"noOfDpdSixtyInLast24Months":0,"noOfDpdOneInLast3Months":0},{"accountNumber":"MKB3AA622FID33288147","accountType":"Personal Loan","dateReported":"30-04-2022","accountStatus":"Active","disbursedAmount":"1,000","disbursedDate":"05-04-2022","lastPaymentDate":null,"closeDate":null,"installmentAmount":null,"interestRate":null,"overdueAmount":null,"writeoffAmount":"0","currentBalance":"1,050","creditLimit":null,"accountRemarks":null,"frequency":null,"combinedPaymentHistory":"Apr:2022,XXX/STD|","cashLimit":null,"actualPayment":null,"repaymentTenure":null,"disbursedAmountInt":1000,"currentBalanceInt":1050,"overdueAmtInt":0,"writeoffAmountInt":0,"creditLimitInt":0,"latestMonthPayment":{"month":"Apr","year":"2022","dpd":0,"assetClassificationCode":"STD","distanceFromReportDate":2},"totalPayments":1,"installmentAmountInt":33,"isActive":true,"isWrittenOff":false,"isClosed":false,"internalAccountType":"personal","isWrittenOffBasedOnLatestPayment":false,"isDelinquent":false,"isClosedAndNotWrittenOff":false,"noOfMonthsBtwReportDateAndDisbursalDate":2,"maxDpdInLast1Month":0,"maxDpdInLast3Months":0,"maxDpdInLast6Months":0,"maxDpdInLast9Months":0,"maxDpdInLast12Months":0,"noOfTimesDefaulted":0,"isDpdAtLeastOnce":false,"isDpdThirtyAtLeastOnce":false,"isDpdSixtyAtLeastOnce":false,"isDpdNinetyAtLeastOnce":false,"noOfDpdThirtyInLast3Months":0,"noOfDpdThirtyInLast6Months":0,"noOfDpdThirtyInLast9Months":0,"noOfDpdThirtyInLast12Months":0,"noOfDpdThirtyInLast24Months":0,"noOfDpdSixtyInLast3Months":0,"noOfDpdSixtyInLast6Months":0,"noOfDpdSixtyInLast9Months":0,"noOfDpdSixtyInLast12Months":0,"noOfDpdSixtyInLast24Months":0,"noOfDpdOneInLast3Months":0}],"inquiryHistoryStats":{"noOfInqLast10Days":0,"noOfInqLast1Month":1,"noOfInqLast3Month":1,"noOfInqLast6Month":1,"noOfInqLast1Year":1,"total":1},"crifScore":[{"scoreType":"PERFORM CONSUMER 2.0","scoreValue":688,"scoreFactors":"SF01|SF03|SF07|SF30|"}]}