{"requestDetails":{"dateOfRequest":"10-10-2022","reportId":"CCR221010CR179155212","batchId":"1737421169221010"},"personalInformation":{"nameVariations":[{"value":"SANDIRI CHANDRA REDDY","reportedDate":"31-12-2021"},{"value":"B'SANDIRI' B'REDDY'","reportedDate":"31-08-2022"},{"value":"SANDIRI REDDY","reportedDate":"31-01-2022"}],"addressVariations":[{"value":"H NO 3 43 POCHAMMA GALLI KAMAR EDDY MAND AL KYASAMPALLE NIZAMA BAD 503111 TS","reportedDate":"31-08-2022"},{"value":"3 43 POCHAMMAGALLY, KYASAMPALLY KAMAREDD, ., NIZAMABAD, KAMAREDDY KAMAREDDY TS, TS, IN 2709 TELANGANA 503111 TS","reportedDate":"31-08-2022"},{"value":"343 POCHAMMA GALI KYASAMPALLE KEYSANPALLI B.O NIZAMABAD, TELANGANA 503111 TS","reportedDate":"31-12-2021"},{"value":"S/O: SANDIRI MALLA REDDY, H NO 3-43, POCHAMMA GALLI, , KAMAREDDY MANDAL POCHAMMA GALLI , NIZAMABAD,  66 503111 AP","reportedDate":"30-04-2022"},{"value":"3 43 POCHAMMAGALLY  KYASAMPALLY KAMAREDD NIZAMABAD TS 503111 TS","reportedDate":"30-09-2022"}],"panVariations":[{"value":"MHRPS5430C","reportedDate":"30-09-2022"}],"uidVariations":[{"value":"XXXXXXXX1950","reportedDate":"31-12-2021"}],"otherIdVariations":[],"drivingLicenseVariations":[{"value":"TS31620160002594","reportedDate":"30-09-2022"}],"dateOfBirthVariations":[{"value":"01-01-1996","reportedDate":"31-12-2021"},{"value":"04-02-1996","reportedDate":"30-09-2022"}],"voterIdVariations":[],"passportVariations":[],"phoneNumberVariations":[{"value":"9908873507","reportedDate":"30-09-2022"}],"rationCardVariations":[],"emailVariations":[{"value":"chandrareddysandi@gmail.com","reportedDate":"31-12-2021"},{"value":"sandirichandrareddy@gmail.com","reportedDate":"31-08-2022"}]},"tradesSummary":[{"accountNumber":"4212MSL00011577","accountType":"Gold Loan","dateReported":"31-12-2021","accountStatus":"Active","disbursedAmount":"1,99,900","disbursedDate":"19-10-2020","lastPaymentDate":null,"closeDate":null,"installmentAmount":null,"interestRate":"24.0","overdueAmount":"0","writeoffAmount":"0","currentBalance":"1,99,900","creditLimit":null,"accountRemarks":null,"frequency":null,"combinedPaymentHistory":"Dec:2021,000/XXX|Nov:2021,000/XXX|Oct:2021,000/XXX|Sep:2021,XXX/XXX|Aug:2021,XXX/XXX|Jul:2021,XXX/XXX|Jun:2021,XXX/XXX|May:2021,XXX/XXX|Apr:2021,XXX/XXX|Mar:2021,XXX/XXX|Feb:2021,XXX/XXX|Jan:2021,XXX/XXX|Dec:2020,XXX/XXX|Nov:2020,XXX/XXX|","cashLimit":null,"actualPayment":null,"repaymentTenure":null,"disbursedAmountInt":199900,"currentBalanceInt":199900,"overdueAmtInt":0,"writeoffAmountInt":0,"creditLimitInt":0,"latestMonthPayment":{"month":"Dec","year":"2021","dpd":0,"assetClassificationCode":"XXX","distanceFromReportDate":10},"totalPayments":14,"installmentAmountInt":9410,"isActive":false,"isWrittenOff":false,"isClosed":true,"internalAccountType":"securedpl","isWrittenOffBasedOnLatestPayment":false,"isDelinquent":false,"isClosedAndNotWrittenOff":true,"noOfMonthsBtwReportDateAndDisbursalDate":23,"maxDpdInLast1Month":0,"maxDpdInLast3Months":0,"maxDpdInLast6Months":0,"maxDpdInLast9Months":0,"maxDpdInLast12Months":0,"noOfTimesDefaulted":0,"isDpdAtLeastOnce":false,"isDpdThirtyAtLeastOnce":false,"isDpdSixtyAtLeastOnce":false,"isDpdNinetyAtLeastOnce":false,"noOfDpdThirtyInLast3Months":0,"noOfDpdThirtyInLast6Months":0,"noOfDpdThirtyInLast9Months":0,"noOfDpdThirtyInLast12Months":0,"noOfDpdThirtyInLast24Months":0,"noOfDpdSixtyInLast3Months":0,"noOfDpdSixtyInLast6Months":0,"noOfDpdSixtyInLast9Months":0,"noOfDpdSixtyInLast12Months":0,"noOfDpdSixtyInLast24Months":0,"noOfDpdOneInLast3Months":0},{"accountNumber":"4212MSL00011966","accountType":"Gold Loan","dateReported":"31-12-2021","accountStatus":"Active","disbursedAmount":"1,99,900","disbursedDate":"30-11-2020","lastPaymentDate":null,"closeDate":null,"installmentAmount":null,"interestRate":"24.0","overdueAmount":"0","writeoffAmount":"0","currentBalance":"1,99,900","creditLimit":null,"accountRemarks":null,"frequency":null,"combinedPaymentHistory":"Dec:2021,000/XXX|Nov:2021,XXX/XXX|Oct:2021,XXX/XXX|Sep:2021,XXX/XXX|Aug:2021,XXX/XXX|Jul:2021,XXX/XXX|Jun:2021,XXX/XXX|May:2021,XXX/XXX|Apr:2021,XXX/XXX|Mar:2021,XXX/XXX|Feb:2021,XXX/XXX|Jan:2021,XXX/XXX|Dec:2020,XXX/XXX|","cashLimit":null,"actualPayment":null,"repaymentTenure":null,"disbursedAmountInt":199900,"currentBalanceInt":199900,"overdueAmtInt":0,"writeoffAmountInt":0,"creditLimitInt":0,"latestMonthPayment":{"month":"Dec","year":"2021","dpd":0,"assetClassificationCode":"XXX","distanceFromReportDate":10},"totalPayments":13,"installmentAmountInt":9410,"isActive":false,"isWrittenOff":false,"isClosed":true,"internalAccountType":"securedpl","isWrittenOffBasedOnLatestPayment":false,"isDelinquent":false,"isClosedAndNotWrittenOff":true,"noOfMonthsBtwReportDateAndDisbursalDate":22,"maxDpdInLast1Month":0,"maxDpdInLast3Months":0,"maxDpdInLast6Months":0,"maxDpdInLast9Months":0,"maxDpdInLast12Months":0,"noOfTimesDefaulted":0,"isDpdAtLeastOnce":false,"isDpdThirtyAtLeastOnce":false,"isDpdSixtyAtLeastOnce":false,"isDpdNinetyAtLeastOnce":false,"noOfDpdThirtyInLast3Months":0,"noOfDpdThirtyInLast6Months":0,"noOfDpdThirtyInLast9Months":0,"noOfDpdThirtyInLast12Months":0,"noOfDpdThirtyInLast24Months":0,"noOfDpdSixtyInLast3Months":0,"noOfDpdSixtyInLast6Months":0,"noOfDpdSixtyInLast9Months":0,"noOfDpdSixtyInLast12Months":0,"noOfDpdSixtyInLast24Months":0,"noOfDpdOneInLast3Months":0},{"accountNumber":"BAN22E002202023","accountType":"Consumer Loan","dateReported":"30-09-2022","accountStatus":"Active","disbursedAmount":"1,500","disbursedDate":"19-09-2022","lastPaymentDate":null,"closeDate":null,"installmentAmount":null,"interestRate":null,"overdueAmount":"0","writeoffAmount":"0","currentBalance":"0","creditLimit":null,"accountRemarks":null,"frequency":null,"combinedPaymentHistory":"Sep:2022,000/STD|","cashLimit":null,"actualPayment":null,"repaymentTenure":null,"disbursedAmountInt":1500,"currentBalanceInt":0,"overdueAmtInt":0,"writeoffAmountInt":0,"creditLimitInt":0,"latestMonthPayment":{"month":"Sep","year":"2022","dpd":0,"assetClassificationCode":"STD","distanceFromReportDate":1},"totalPayments":1,"installmentAmountInt":91,"isActive":true,"isWrittenOff":false,"isClosed":false,"internalAccountType":"consumer","isWrittenOffBasedOnLatestPayment":false,"isDelinquent":false,"isClosedAndNotWrittenOff":false,"noOfMonthsBtwReportDateAndDisbursalDate":0,"maxDpdInLast1Month":0,"maxDpdInLast3Months":0,"maxDpdInLast6Months":0,"maxDpdInLast9Months":0,"maxDpdInLast12Months":0,"noOfTimesDefaulted":0,"isDpdAtLeastOnce":false,"isDpdThirtyAtLeastOnce":false,"isDpdSixtyAtLeastOnce":false,"isDpdNinetyAtLeastOnce":false,"noOfDpdThirtyInLast3Months":0,"noOfDpdThirtyInLast6Months":0,"noOfDpdThirtyInLast9Months":0,"noOfDpdThirtyInLast12Months":0,"noOfDpdThirtyInLast24Months":0,"noOfDpdSixtyInLast3Months":0,"noOfDpdSixtyInLast6Months":0,"noOfDpdSixtyInLast9Months":0,"noOfDpdSixtyInLast12Months":0,"noOfDpdSixtyInLast24Months":0,"noOfDpdOneInLast3Months":0},{"accountNumber":"4212MSL00010899","accountType":"Gold Loan","dateReported":"28-10-2020","accountStatus":"Closed","disbursedAmount":"42,000","disbursedDate":"12-08-2020","lastPaymentDate":"28-10-2020","closeDate":null,"installmentAmount":null,"interestRate":"24.0","overdueAmount":"0","writeoffAmount":"0","currentBalance":"0","creditLimit":null,"accountRemarks":null,"frequency":null,"combinedPaymentHistory":"Oct:2020,000/XXX|Sep:2020,000/XXX|Aug:2020,000/XXX|","cashLimit":null,"actualPayment":null,"repaymentTenure":null,"disbursedAmountInt":42000,"currentBalanceInt":0,"overdueAmtInt":0,"writeoffAmountInt":0,"creditLimitInt":0,"latestMonthPayment":{"month":"Oct","year":"2020","dpd":0,"assetClassificationCode":"XXX","distanceFromReportDate":24},"totalPayments":3,"installmentAmountInt":1977,"isActive":false,"isWrittenOff":false,"isClosed":true,"internalAccountType":"securedpl","isWrittenOffBasedOnLatestPayment":false,"isDelinquent":false,"isClosedAndNotWrittenOff":true,"noOfMonthsBtwReportDateAndDisbursalDate":25,"maxDpdInLast1Month":0,"maxDpdInLast3Months":0,"maxDpdInLast6Months":0,"maxDpdInLast9Months":0,"maxDpdInLast12Months":0,"noOfTimesDefaulted":0,"isDpdAtLeastOnce":false,"isDpdThirtyAtLeastOnce":false,"isDpdSixtyAtLeastOnce":false,"isDpdNinetyAtLeastOnce":false,"noOfDpdThirtyInLast3Months":0,"noOfDpdThirtyInLast6Months":0,"noOfDpdThirtyInLast9Months":0,"noOfDpdThirtyInLast12Months":0,"noOfDpdThirtyInLast24Months":0,"noOfDpdSixtyInLast3Months":0,"noOfDpdSixtyInLast6Months":0,"noOfDpdSixtyInLast9Months":0,"noOfDpdSixtyInLast12Months":0,"noOfDpdSixtyInLast24Months":0,"noOfDpdOneInLast3Months":0},{"accountNumber":"4212MSL00011674","accountType":"Gold Loan","dateReported":"17-11-2020","accountStatus":"Closed","disbursedAmount":"27,950","disbursedDate":"28-10-2020","lastPaymentDate":null,"closeDate":null,"installmentAmount":null,"interestRate":"24.0","overdueAmount":"0","writeoffAmount":"0","currentBalance":"0","creditLimit":null,"accountRemarks":null,"frequency":null,"combinedPaymentHistory":"Nov:2020,000/XXX|Oct:2020,000/XXX|","cashLimit":null,"actualPayment":null,"repaymentTenure":null,"disbursedAmountInt":27950,"currentBalanceInt":0,"overdueAmtInt":0,"writeoffAmountInt":0,"creditLimitInt":0,"latestMonthPayment":{"month":"Nov","year":"2020","dpd":0,"assetClassificationCode":"XXX","distanceFromReportDate":23},"totalPayments":2,"installmentAmountInt":1316,"isActive":false,"isWrittenOff":false,"isClosed":true,"internalAccountType":"securedpl","isWrittenOffBasedOnLatestPayment":false,"isDelinquent":false,"isClosedAndNotWrittenOff":true,"noOfMonthsBtwReportDateAndDisbursalDate":23,"maxDpdInLast1Month":0,"maxDpdInLast3Months":0,"maxDpdInLast6Months":0,"maxDpdInLast9Months":0,"maxDpdInLast12Months":0,"noOfTimesDefaulted":0,"isDpdAtLeastOnce":false,"isDpdThirtyAtLeastOnce":false,"isDpdSixtyAtLeastOnce":false,"isDpdNinetyAtLeastOnce":false,"noOfDpdThirtyInLast3Months":0,"noOfDpdThirtyInLast6Months":0,"noOfDpdThirtyInLast9Months":0,"noOfDpdThirtyInLast12Months":0,"noOfDpdThirtyInLast24Months":0,"noOfDpdSixtyInLast3Months":0,"noOfDpdSixtyInLast6Months":0,"noOfDpdSixtyInLast9Months":0,"noOfDpdSixtyInLast12Months":0,"noOfDpdSixtyInLast24Months":0,"noOfDpdOneInLast3Months":0},{"accountNumber":"PYTMPPABFL8275901414994","accountType":"Other","dateReported":"31-08-2022","accountStatus":"Active","disbursedAmount":"2,000","disbursedDate":"25-11-2021","lastPaymentDate":"05-08-2022","closeDate":null,"installmentAmount":"0","interestRate":null,"overdueAmount":"0","writeoffAmount":"0","currentBalance":"1,773","creditLimit":null,"accountRemarks":null,"frequency":null,"combinedPaymentHistory":"Aug:2022,000/STD|Jul:2022,000/STD|Jun:2022,000/STD|May:2022,000/STD|Apr:2022,000/STD|Mar:2022,000/STD|Feb:2022,000/STD|Jan:2022,000/STD|Dec:2021,000/STD|Nov:2021,000/STD|","cashLimit":null,"actualPayment":null,"repaymentTenure":null,"disbursedAmountInt":2000,"currentBalanceInt":1773,"overdueAmtInt":0,"writeoffAmountInt":0,"creditLimitInt":0,"latestMonthPayment":{"month":"Aug","year":"2022","dpd":0,"assetClassificationCode":"STD","distanceFromReportDate":2},"totalPayments":10,"installmentAmountInt":66,"isActive":true,"isWrittenOff":false,"isClosed":false,"internalAccountType":"other","isWrittenOffBasedOnLatestPayment":false,"isDelinquent":false,"isClosedAndNotWrittenOff":false,"noOfMonthsBtwReportDateAndDisbursalDate":10,"maxDpdInLast1Month":0,"maxDpdInLast3Months":0,"maxDpdInLast6Months":0,"maxDpdInLast9Months":0,"maxDpdInLast12Months":0,"noOfTimesDefaulted":0,"isDpdAtLeastOnce":false,"isDpdThirtyAtLeastOnce":false,"isDpdSixtyAtLeastOnce":false,"isDpdNinetyAtLeastOnce":false,"noOfDpdThirtyInLast3Months":0,"noOfDpdThirtyInLast6Months":0,"noOfDpdThirtyInLast9Months":0,"noOfDpdThirtyInLast12Months":0,"noOfDpdThirtyInLast24Months":0,"noOfDpdSixtyInLast3Months":0,"noOfDpdSixtyInLast6Months":0,"noOfDpdSixtyInLast9Months":0,"noOfDpdSixtyInLast12Months":0,"noOfDpdSixtyInLast24Months":0,"noOfDpdOneInLast3Months":0},{"accountNumber":"83012876","accountType":"Personal Loan","dateReported":"31-08-2022","accountStatus":"Active","disbursedAmount":"1,50,000","disbursedDate":"02-08-2022","lastPaymentDate":"02-08-2022","closeDate":null,"installmentAmount":null,"interestRate":null,"overdueAmount":"0","writeoffAmount":"0","currentBalance":"1,50,000","creditLimit":null,"accountRemarks":null,"frequency":null,"combinedPaymentHistory":"Aug:2022,000/XXX|","cashLimit":null,"actualPayment":"1","repaymentTenure":null,"disbursedAmountInt":150000,"currentBalanceInt":150000,"overdueAmtInt":0,"writeoffAmountInt":0,"creditLimitInt":0,"latestMonthPayment":{"month":"Aug","year":"2022","dpd":0,"assetClassificationCode":"XXX","distanceFromReportDate":2},"totalPayments":1,"installmentAmountInt":4982,"isActive":true,"isWrittenOff":false,"isClosed":false,"internalAccountType":"personal","isWrittenOffBasedOnLatestPayment":false,"isDelinquent":false,"isClosedAndNotWrittenOff":false,"noOfMonthsBtwReportDateAndDisbursalDate":2,"maxDpdInLast1Month":0,"maxDpdInLast3Months":0,"maxDpdInLast6Months":0,"maxDpdInLast9Months":0,"maxDpdInLast12Months":0,"noOfTimesDefaulted":0,"isDpdAtLeastOnce":false,"isDpdThirtyAtLeastOnce":false,"isDpdSixtyAtLeastOnce":false,"isDpdNinetyAtLeastOnce":false,"noOfDpdThirtyInLast3Months":0,"noOfDpdThirtyInLast6Months":0,"noOfDpdThirtyInLast9Months":0,"noOfDpdThirtyInLast12Months":0,"noOfDpdThirtyInLast24Months":0,"noOfDpdSixtyInLast3Months":0,"noOfDpdSixtyInLast6Months":0,"noOfDpdSixtyInLast9Months":0,"noOfDpdSixtyInLast12Months":0,"noOfDpdSixtyInLast24Months":0,"noOfDpdOneInLast3Months":0},{"accountNumber":"28685493","accountType":"Personal Loan","dateReported":"31-08-2022","accountStatus":"Active","disbursedAmount":"10,000","disbursedDate":"16-12-2019","lastPaymentDate":"05-11-2020","closeDate":null,"installmentAmount":"0/Monthly","interestRate":null,"overdueAmount":"0","writeoffAmount":"0","currentBalance":"0","creditLimit":null,"accountRemarks":null,"frequency":null,"combinedPaymentHistory":"Aug:2022,000/XXX|Jul:2022,000/XXX|Jun:2022,000/XXX|May:2022,000/XXX|Apr:2022,000/XXX|Mar:2022,000/XXX|Feb:2022,000/XXX|Jan:2022,000/XXX|Dec:2021,000/XXX|Nov:2021,000/XXX|Oct:2021,000/XXX|Sep:2021,000/XXX|Aug:2021,000/XXX|Jul:2021,000/XXX|Jun:2021,000/XXX|May:2021,000/XXX|Apr:2021,000/XXX|Mar:2021,000/XXX|Feb:2021,000/XXX|Jan:2021,000/XXX|Dec:2020,000/XXX|Nov:2020,000/XXX|Oct:2020,000/XXX|Sep:2020,000/XXX|Aug:2020,000/XXX|Jul:2020,000/XXX|Jun:2020,000/XXX|May:2020,000/XXX|Apr:2020,000/XXX|Mar:2020,000/XXX|Feb:2020,000/XXX|Jan:2020,000/XXX|Dec:2019,000/XXX|","cashLimit":null,"actualPayment":"16,766","repaymentTenure":null,"disbursedAmountInt":10000,"currentBalanceInt":0,"overdueAmtInt":0,"writeoffAmountInt":0,"creditLimitInt":0,"latestMonthPayment":{"month":"Aug","year":"2022","dpd":0,"assetClassificationCode":"XXX","distanceFromReportDate":2},"totalPayments":33,"installmentAmountInt":0,"isActive":true,"isWrittenOff":false,"isClosed":false,"internalAccountType":"personal","isWrittenOffBasedOnLatestPayment":false,"isDelinquent":false,"isClosedAndNotWrittenOff":false,"noOfMonthsBtwReportDateAndDisbursalDate":33,"maxDpdInLast1Month":0,"maxDpdInLast3Months":0,"maxDpdInLast6Months":0,"maxDpdInLast9Months":0,"maxDpdInLast12Months":0,"noOfTimesDefaulted":0,"isDpdAtLeastOnce":false,"isDpdThirtyAtLeastOnce":false,"isDpdSixtyAtLeastOnce":false,"isDpdNinetyAtLeastOnce":false,"noOfDpdThirtyInLast3Months":0,"noOfDpdThirtyInLast6Months":0,"noOfDpdThirtyInLast9Months":0,"noOfDpdThirtyInLast12Months":0,"noOfDpdThirtyInLast24Months":0,"noOfDpdSixtyInLast3Months":0,"noOfDpdSixtyInLast6Months":0,"noOfDpdSixtyInLast9Months":0,"noOfDpdSixtyInLast12Months":0,"noOfDpdSixtyInLast24Months":0,"noOfDpdOneInLast3Months":0}],"inquiryHistoryStats":{"noOfInqLast10Days":0,"noOfInqLast1Month":0,"noOfInqLast3Month":0,"noOfInqLast6Month":1,"noOfInqLast1Year":1,"total":1},"crifScore":[{"scoreType":"PERFORM CONSUMER 2.0","scoreValue":645,"scoreFactors":"SF01|SF13|SF15|SF30|"}]}